setup.py
benchmark/__init__.py
benchmark/test_octopus.py
octopus/__init__.py
octopus/cache.py
octopus/core.py
octopus/model.py
octopus/tornado_core.py
octopus/limiter/__init__.py
octopus/limiter/in_memory/__init__.py
octopus/limiter/in_memory/per_domain.py
octopus/limiter/redis/__init__.py
octopus/limiter/redis/per_domain.py
octopus_http.egg-info/PKG-INFO
octopus_http.egg-info/SOURCES.txt
octopus_http.egg-info/dependency_links.txt
octopus_http.egg-info/requires.txt
octopus_http.egg-info/top_level.txt
tests/__init__.py
tests/test_cache.py
tests/test_model.py
tests/test_octopus.py
tests/test_octopus_limited.py
tests/test_tornado_octopus.py
tests/test_tornado_octopus_limited.py
tests/limiter/__init__.py
tests/limiter/in_memory/__init__.py
tests/limiter/in_memory/test_per_domain.py
tests/limiter/redis/__init__.py
tests/limiter/redis/test_per_domain.py